MANIFEST.in
README.md
setup.py
openhwcontrol/__init__.py
openhwcontrol/cooler.py
openhwcontrol/grid.py
openhwcontrol/gui.py
openhwcontrol/helper.py
openhwcontrol/openhwmon.py
openhwcontrol/polling.py
openhwcontrol/settings.py
openhwcontrol/ui.py
openhwcontrol.egg-info/PKG-INFO
openhwcontrol.egg-info/SOURCES.txt
openhwcontrol.egg-info/dependency_links.txt
openhwcontrol.egg-info/entry_points.txt
openhwcontrol.egg-info/not-zip-safe
openhwcontrol.egg-info/requires.txt
openhwcontrol.egg-info/top_level.txt