Metadata-Version: 1.1
Name: openhwcontrol
Version: 1.0.0
Summary: A cross platform open source tool to control NZXT components easily through software
Home-page: http://github.com/kusti8/openhwcontrol
Author: Gustav Hansen
Author-email: kusti8@gmail.com
License: GPL3
Keywords: nzxt hue hue-plus hue_plus hue+ openhwcontrol kraken
Platform: UNKNOWN
Classifier: Development Status :: 5 - Production/Stable
Classifier: License :: OSI Approved :: GNU General Public License v3 or later (GPLv3+)
Classifier: Programming Language :: Python :: 3 :: Only
